Metadata-Version: 2.1
Name: pyfontingtoolsV1
Version: 1.0.0
Summary: Usefull utility package
Home-page: UNKNOWN
Author: Christian F
Author-email: nick.faltermeier@gmx.de
License: UNKNOWN
Keywords: python
Platform: UNKNOWN
Classifier: Operating System :: Microsoft :: Windows
